<?xml version = '1.0' encoding = 'UTF-8'?>
<Relation class="oracle.dbtools.crest.model.design.logical.Relation" name="Relation_48" directorySegmentName="seg_0" id="292E6325-8869-DD0A-BAAB-F53BD44FAAB7">
<createdBy>Kielx</createdBy>
<createdTime>2022-11-19 22:19:22 UTC</createdTime>
<ownerDesignName>model</ownerDesignName>
<engineerTo>
<item key="CF0721B3-C64F-C74B-FC31-80FA06AE66FF" value="true"/>
</engineerTo>
<sourcePk>D109A322-9BBE-E845-38B6-66893A94E762</sourcePk>
<identifying>false</identifying>
<optionalSource>true</optionalSource>
<optionalTarget>false</optionalTarget>
<sourceCardinality>1</sourceCardinality>
<sourceEntity>326F699D-CDF7-D4A4-170D-0547B58A059B</sourceEntity>
<targetCardinalityString>*</targetCardinalityString>
<targetEntity>4E43829A-60AA-6E41-9D89-3A73A17C3F1E</targetEntity>
<transferable>true</transferable>
<deleteRule>NO ACTION</deleteRule>
</Relation>